{"stats":{"minecraft:crafted":{"minecraft:oak_planks":387,"minecraft:stone_brick_wall":42,"minecraft:smooth_stone_slab":78,"minecraft:iron_nugget":576,"minecraft:stone_button":2,"minecraft:lever":1,"minecraft:bone_meal":3,"minecraft:hopper":1,"minecraft:lantern":71,"minecraft:stone_brick_slab":12,"minecraft:repeater":2,"minecraft:bow":11,"minecraft:iron_axe":2,"minecraft:iron_hoe":1,"minecraft:chest":8,"minecraft:redstone_block":2,"minecraft:dark_oak_planks":400,"minecraft:stone_bricks":136,"minecraft:dropper":1,"minecraft:redstone_lamp":15,"minecraft:crafting_table":3,"minecraft:hay_block":7,"minecraft:bucket":39,"minecraft:glowstone":4,"minecraft:dispenser":11,"minecraft:oak_fence_gate":19,"minecraft:dark_oak_slab":120,"minecraft:white_wool":6,"minecraft:white_dye":2,"minecraft:stick":152,"minecraft:compass":1,"minecraft:iron_pickaxe":11,"minecraft:iron_shovel":3,"minecraft:white_bed":2,"minecraft:redstone_torch":30,"minecraft:torch":76,"minecraft:shears":1},"minecraft:dropped":{"minecraft:water_bucket":2,"minecraft:crafting_table":1,"minecraft:cobblestone":1,"minecraft:lantern":1,"minecraft:apple":5,"minecraft:stick":13,"minecraft:flint":23,"minecraft:torch":1,"minecraft:dispenser":11,"minecraft:bone_meal":1,"minecraft:smooth_stone":50,"minecraft:bucket":7,"minecraft:iron_nugget":20,"minecraft:oak_planks":64,"minecraft:shears":1,"minecraft:poppy":1,"minecraft:oak_fence_gate":2,"minecraft:bow":1},"minecraft:custom":{"minecraft:mob_kills":6,"minecraft:inspect_hopper":10,"minecraft:interact_with_crafting_table":117,"minecraft:open_barrel":206,"minecraft:leave_game":11,"minecraft:time_since_death":804026,"minecraft:climb_one_cm":1692,"minecraft:sprint_one_cm":718451,"minecraft:walk_one_cm":5432439,"minecraft:drop":38,"minecraft:sneak_time":6372,"minecraft:walk_under_water_one_cm":305832,"minecraft:jump":4319,"minecraft:walk_on_water_one_cm":441910,"minecraft:interact_with_furnace":7,"minecraft:play_one_minute":804026,"minecraft:interact_with_stonecutter":4,"minecraft:sleep_in_bed":24,"minecraft:time_since_rest":19925,"minecraft:damage_taken":1470,"minecraft:damage_dealt":899,"minecraft:swim_one_cm":867,"minecraft:fly_one_cm":31526,"minecraft:open_chest":360,"minecraft:crouch_one_cm":20850,"minecraft:inspect_dispenser":26,"minecraft:fall_one_cm":61304,"minecraft:horse_one_cm":16292},"minecraft:mined":{"minecraft:dark_oak_planks":66,"minecraft:red_carpet":1,"minecraft:white_bed":3,"minecraft:cobblestone_stairs":21,"minecraft:dark_oak_log":3,"minecraft:stone_button":1,"minecraft:grass_block":300,"minecraft:stone_brick_wall":13,"minecraft:redstone_wire":16,"minecraft:hopper":1,"minecraft:kelp":18,"minecraft:hay_block":5,"minecraft:smooth_stone":141,"minecraft:oak_trapdoor":7,"minecraft:carrots":47,"minecraft:oak_stairs":14,"minecraft:lantern":31,"minecraft:stripped_oak_log":4,"minecraft:stone":1942,"minecraft:white_wool":1,"minecraft:redstone_wall_torch":5,"minecraft:kelp_plant":23,"minecraft:stone_brick_slab":25,"minecraft:dandelion":1,"minecraft:clay":13,"minecraft:crafting_table":1,"minecraft:torch":9,"minecraft:poppy":1,"minecraft:dropper":1,"minecraft:chest":3,"minecraft:glass":237,"minecraft:cobblestone":112,"minecraft:oak_planks":26,"minecraft:wall_torch":17,"minecraft:seagrass":1,"minecraft:purple_wool":21,"minecraft:dark_oak_slab":20,"minecraft:birch_log":11,"minecraft:redstone_torch":9,"minecraft:wheat":68,"minecraft:birch_leaves":8,"minecraft:smooth_stone_slab":49,"minecraft:grass":106,"minecraft:oak_log":104,"minecraft:coal_ore":19,"minecraft:oak_fence_gate":1,"minecraft:gravel":126,"minecraft:sand":407,"minecraft:dirt":403,"minecraft:stone_bricks":43,"minecraft:oak_leaves":44,"minecraft:redstone_lamp":11},"minecraft:killed":{"minecraft:chicken":1,"minecraft:bat":1,"minecraft:creeper":1,"minecraft:zombie":3},"minecraft:picked_up":{"minecraft:crafting_table":3,"minecraft:wheat":81,"minecraft:purple_wool":113,"minecraft:chicken":1,"minecraft:clay_ball":52,"minecraft:redstone_lamp":11,"minecraft:oak_stairs":14,"minecraft:stone_brick_wall":13,"minecraft:string":77,"minecraft:oak_trapdoor":6,"minecraft:smooth_stone_slab":55,"minecraft:pufferfish":1,"minecraft:smooth_stone":199,"minecraft:bucket":6,"minecraft:rose_bush":2,"minecraft:redstone_torch":28,"minecraft:iron_nugget":18,"minecraft:poppy":1,"minecraft:chest":3,"minecraft:birch_sapling":5,"minecraft:egg":61,"minecraft:stick":32,"minecraft:torch":36,"minecraft:stone_button":1,"minecraft:carrot":170,"minecraft:redstone":53,"minecraft:dark_oak_planks":66,"minecraft:rotten_flesh":4,"minecraft:light_blue_wool":3,"minecraft:shears":1,"minecraft:hay_block":5,"minecraft:cod":8,"minecraft:white_wool":2,"minecraft:cobblestone":1980,"minecraft:stripped_oak_log":5,"minecraft:birch_log":11,"minecraft:feather":2,"minecraft:water_bucket":11,"minecraft:filled_map":1,"minecraft:flint":26,"minecraft:oak_log":103,"minecraft:cobblestone_stairs":17,"minecraft:dirt":690,"minecraft:lantern":46,"minecraft:red_carpet":2,"minecraft:glass":4,"minecraft:apple":5,"minecraft:stone_bricks":43,"minecraft:kelp":83,"minecraft:bow":2,"minecraft:wheat_seeds":254,"minecraft:iron_ingot":32,"minecraft:oak_fence_gate":1,"minecraft:glowstone_dust":2,"minecraft:oak_planks":53,"minecraft:tropical_fish_bucket":1,"minecraft:oak_slab":3,"minecraft:dark_oak_slab":30,"minecraft:stone_brick_slab":25,"minecraft:red_wool":2,"minecraft:dandelion":3,"minecraft:dropper":1,"minecraft:gravel":114,"minecraft:sand":388,"minecraft:white_bed":3,"minecraft:dark_oak_log":3,"minecraft:dispenser":11,"minecraft:oak_sapling":11,"minecraft:coal":19,"minecraft:hopper":1},"minecraft:broken":{"minecraft:iron_shovel":3,"minecraft:iron_axe":1,"minecraft:iron_pickaxe":10},"minecraft:used":{"minecraft:oak_trapdoor":43,"minecraft:iron_shovel":959,"minecraft:dispenser":8,"minecraft:redstone":51,"minecraft:chest":10,"minecraft:spruce_planks":1,"minecraft:stone":322,"minecraft:iron_sword":12,"minecraft:cooked_chicken":19,"minecraft:torch":39,"minecraft:dirt":607,"minecraft:hopper":2,"minecraft:carrot":64,"minecraft:cod_bucket":40,"minecraft:oak_fence_gate":18,"minecraft:milk_bucket":2,"minecraft:glass":498,"minecraft:iron_hoe":125,"minecraft:stone_brick_slab":52,"minecraft:dark_oak_planks":341,"minecraft:lantern":116,"minecraft:iron_axe":296,"minecraft:oak_stairs":74,"minecraft:dark_oak_slab":90,"minecraft:stone_bricks":160,"minecraft:repeater":2,"minecraft:redstone_lamp":24,"minecraft:red_carpet":1,"minecraft:hay_block":12,"minecraft:cooked_cod":13,"minecraft:egg":9,"minecraft:cooked_beef":3,"minecraft:wheat_seeds":527,"minecraft:water_bucket":210,"minecraft:cobblestone_stairs":69,"minecraft:dropper":1,"minecraft:oak_planks":243,"minecraft:redstone_block":2,"minecraft:white_wool":1,"minecraft:sand":78,"minecraft:crafting_table":4,"minecraft:white_bed":5,"minecraft:cod":3,"minecraft:stone_brick_wall":53,"minecraft:shears":4,"minecraft:oak_log":44,"minecraft:redstone_torch":47,"minecraft:lever":1,"minecraft:apple":1,"minecraft:dark_oak_log":3,"minecraft:iron_pickaxe":2574,"minecraft:stone_button":2,"minecraft:gravel":13,"minecraft:cobblestone":112,"minecraft:pufferfish_bucket":3,"minecraft:bucket":292,"minecraft:smooth_stone_slab":133,"minecraft:stripped_oak_log":5,"minecraft:tropical_fish_bucket":11,"minecraft:kelp":82,"minecraft:purple_wool":102,"minecraft:smooth_stone":583}},"DataVersion":1976}